selenia/__init__.py
selenia/main.py
selenia/ollama_model_client.py
selenia-0.2.0.dist-info/METADATA
selenia-0.2.0.dist-info/WHEEL
selenia-0.2.0.dist-info/top_level.txt
selenia-0.2.0.dist-info/RECORD
