Metadata-Version: 2.4
Name: selenia
Version: 0.2.0
Summary: Selenium wrapper to find XPath from natural language using LLMs
Author: Penielny
Author-email: penielnyinaku@gmail.com
Classifier: Programming Language :: Python :: 3
Classifier: Operating System :: OS Independent
Requires-Python: >=3.7
Requires-Dist: selenium
Requires-Dist: requests
Requires-Dist: ollama
Dynamic: author
Dynamic: author-email
Dynamic: classifier
Dynamic: description
Dynamic: description-content-type
Dynamic: requires-dist
Dynamic: requires-python
Dynamic: summary
